dataengineer/__init__.py
dataengineer/base.py
dataengineer/conf.py
dataengineer/database.py
dataengineer/datacls.py
dataengineer/datafile.py
dataengineer/finder.py
dataengineer/models.py
dataengineer/dba/__init__.py
dataengineer/dba/coll_level.py
dataengineer/dba/db_level.py
dataengineer/dba/dba.py
dataengineer/dba/rt.py
DataEngineer-0.2.9.dist-info/LICENSE
DataEngineer-0.2.9.dist-info/METADATA
DataEngineer-0.2.9.dist-info/WHEEL
DataEngineer-0.2.9.dist-info/top_level.txt
DataEngineer-0.2.9.dist-info/RECORD
