Metadata-Version: 2.1
Name: DataEngineer
Version: 0.2.9
Summary: innovata-DataEngineer
Home-page: https://github.com/innovata/DataEngineer
Author: innovata sambong
Author-email: iinnovata@gmail.com
Classifier: Programming Language :: Python :: 3
Classifier: License :: OSI Approved :: MIT License
Classifier: Operating System :: OS Independent
Requires-Python: >=3.8
License-File: LICENSE
Requires-Dist: iDevEnv
